jadio_code/__init__.py
jadio_code/Backend/main/code_aigent/aigent_bottombox_core.py
jadio_code/Backend/main/code_aigent/aigent_chatwindow_core.py
jadio_code/Backend/main/code_aigent/aigent_core.py
jadio_code/Backend/main/code_aigent/aigent_sidebar_core.py
jadio_code/Backend/main/code_aigent/aigent_terminal_core.py
jadio_code/Backend/main/code_aigent/aigent_topbox_core.py
jadio_code/Backend/main/editor/editor_core.py
jadio_code/Backend/main/explorer/exploer_sidebar_core.py
jadio_code/Backend/main/explorer/explorer_core.py
jadio_code/Backend/main/terminal/terminal_core.py
jadio_code/Backend/sub/code_doctor/code_doctor_core.py
jadio_code/Backend/sub/help/help_core.py
jadio_code/Backend/sub/lan/lan_core.py
jadio_code/Backend/sub/llm/llm_core.py
jadio_code/Backend/sub/plugins/plugins_core.py
jadio_code/Backend/sub/settings/settings_core.py
jadio_code/UI/__init__.py
jadio_code/UI/main.py
jadio_code/UI/menubar.py
jadio_code/UI/styles.py
jadio_code/UI/icons/bell.svg
jadio_code/UI/icons/bolt.svg
jadio_code/UI/icons/check.svg
jadio_code/UI/icons/clipboard.svg
jadio_code/UI/icons/clock.svg
jadio_code/UI/icons/cloud.svg
jadio_code/UI/icons/down.svg
jadio_code/UI/icons/download.svg
jadio_code/UI/icons/explorer.svg
jadio_code/UI/icons/eye.svg
jadio_code/UI/icons/folder.svg
jadio_code/UI/icons/folder2.svg
jadio_code/UI/icons/glass.svg
jadio_code/UI/icons/globe.svg
jadio_code/UI/icons/grid.svg
jadio_code/UI/icons/idk.svg
jadio_code/UI/icons/info.svg
jadio_code/UI/icons/left.svg
jadio_code/UI/icons/lock.svg
jadio_code/UI/icons/lock2.svg
jadio_code/UI/icons/message.svg
jadio_code/UI/icons/net.svg
jadio_code/UI/icons/pencil.svg
jadio_code/UI/icons/play.svg
jadio_code/UI/icons/plus.svg
jadio_code/UI/icons/right.svg
jadio_code/UI/icons/robot.svg
jadio_code/UI/icons/split.svg
jadio_code/UI/icons/star.svg
jadio_code/UI/icons/stop.svg
jadio_code/UI/icons/tabs.svg
jadio_code/UI/icons/terminal.svg
jadio_code/UI/icons/up.svg
jadio_code/UI/icons/upload.svg
jadio_code/UI/icons/user.svg
jadio_code-0.0.1.dist-info/METADATA
jadio_code-0.0.1.dist-info/WHEEL
jadio_code-0.0.1.dist-info/entry_points.txt
jadio_code-0.0.1.dist-info/licenses/license.md
jadio_code-0.0.1.dist-info/RECORD
