Metadata-Version: 2.4
Name: jadio-code
Version: 0.0.1
Summary: Local IDE connected to a vibrant LLM ecosystem
Project-URL: Homepage, https://pypi.org/project/jadio/
Project-URL: Repository, https://github.com/JaxxyJadio/jadio
License-Expression: MIT
License-File: license.md
Classifier: Development Status :: 3 - Alpha
Classifier: Intended Audience :: Developers
Classifier: License :: OSI Approved :: MIT License
Classifier: Programming Language :: Python :: 3
Classifier: Programming Language :: Python :: 3.8
Classifier: Programming Language :: Python :: 3.9
Classifier: Programming Language :: Python :: 3.10
Classifier: Programming Language :: Python :: 3.11
Classifier: Programming Language :: Python :: 3.12
Requires-Python: >=3.8
Requires-Dist: requests
Requires-Dist: rich
